OptionGreeksGPU/Compute.py
OptionGreeksGPU/GreeksC.py
OptionGreeksGPU/GreeksGPU.py
OptionGreeksGPU/__init__.py
OptionGreeksGPU-2.0.0.dist-info/LICENSE
OptionGreeksGPU-2.0.0.dist-info/METADATA
OptionGreeksGPU-2.0.0.dist-info/WHEEL
OptionGreeksGPU-2.0.0.dist-info/top_level.txt
OptionGreeksGPU-2.0.0.dist-info/RECORD
