Metadata-Version: 2.1
Name: OptionGreeksGPU
Version: 2.0.0
Summary: GPU / Machine code - accelerated computation of option Greeks
Home-page: https://github.com/SalilBhasinOfficial/OptionGreeksGPU.git
Author: Salil Bhasin
Author-email: salilbhasinofficial@gmail.com
Keywords: options greeks computation gpu acceleration finance options trading quantitative finance risk management financial engineering option pricing CUDA GPU computing high performance computing derivatives trading volatility hedging strategies investment analysis trading algorithms financial markets black-scholes algorithmic trading portfolio optimization market analysis
Classifier: Development Status :: 5 - Production/Stable
Classifier: Intended Audience :: Financial and Insurance Industry
Classifier: Topic :: Office/Business :: Financial :: Investment
Classifier: License :: OSI Approved :: GNU General Public License v3 (GPLv3)
Classifier: Programming Language :: Python :: 3
Classifier: Programming Language :: Python :: 3.7
Classifier: Programming Language :: Python :: 3.8
Classifier: Programming Language :: Python :: 3.9
Classifier: Programming Language :: Python :: 3.10
Requires-Python: >=3.7
License-File: LICENSE
Requires-Dist: numpy
Requires-Dist: numba
Requires-Dist: pandas
